securewipe/__init__.py
securewipe/cli.py
securewipe/core.py
securewipe-3.0.0.dist-info/LICENSE
securewipe-3.0.0.dist-info/METADATA
securewipe-3.0.0.dist-info/WHEEL
securewipe-3.0.0.dist-info/entry_points.txt
securewipe-3.0.0.dist-info/top_level.txt
securewipe-3.0.0.dist-info/RECORD
