Metadata-Version: 2.1
Name: securewipe
Version: 3.0.0
Summary: A Python package for securely wiping files or folders.
Home-page: https://github.com/Bytebreach/securewipe
Author: Fidal
Author-email: mrfidal@proton.me
License: MIT
License-File: LICENSE
